bs_ds/__init__.py
bs_ds/bamboo.py
bs_ds/bs_ds.py
bs_ds/capstone.py
bs_ds/glassboxes.py
bs_ds/importSklearn.py
bs_ds/imports.py
bs_ds/prettypandas.py
bs_ds/saycheese.py
bs_ds/saywhat.py
bs_ds/waldos_work.py
bs_ds-0.11.1.dist-info/AUTHORS.rst
bs_ds-0.11.1.dist-info/LICENSE
bs_ds-0.11.1.dist-info/METADATA
bs_ds-0.11.1.dist-info/WHEEL
bs_ds-0.11.1.dist-info/entry_points.txt
bs_ds-0.11.1.dist-info/top_level.txt
bs_ds-0.11.1.dist-info/RECORD
