Metadata-Version: 2.1
Name: bs-ds
Version: 0.11.1
Summary: A collection of tools from bootcamp.
Home-page: https://github.com/jirvingphd/bs_ds
Author: James Irving
Author-email: james.irving.phd@gmail.com
License: GNU General Public License v3
Keywords: bs_ds
Platform: UNKNOWN
Classifier: Development Status :: 2 - Pre-Alpha
Classifier: Intended Audience :: Developers
Classifier: License :: OSI Approved :: GNU General Public License v3 (GPLv3)
Classifier: Natural Language :: English
Classifier: Programming Language :: Python :: 3.6
Classifier: Programming Language :: Python :: 3.7
Requires-Dist: IPython
Requires-Dist: pprint
Requires-Dist: seaborn
Requires-Dist: tzlocal
Requires-Dist: cufflinks
Requires-Dist: scikit-learn (>=0.22.2)
Requires-Dist: matplotlib (>=3.2)
Requires-Dist: qgrid
Requires-Dist: fake-useragent
Requires-Dist: gensim
Requires-Dist: openpyxl
Requires-Dist: beautifulsoup4
Requires-Dist: xgboost
Requires-Dist: pyperclip
Requires-Dist: tweepy
Requires-Dist: jsonpickle
Requires-Dist: jinja2
Requires-Dist: catboost
Requires-Dist: nltk
